{
    "etablissement": "Campus La Mouillère",
    "groupes": [
      {
        "id": "1",
        "nom": "Administration",
        "mail":" ",
        "telephone":" ",
        "personnes": [
          {
            "nom": "Standard",
            "email": "contact@lamouillere.fr",
            "telephone": "02 38 22 60 80"
          },
          {
            "nom": "AUDRAIN Jean-Philippe",
            "email": "jp.audrain@lamouillere.fr",
            "telephone": "06 23 07 14 98"
          },
          {
            "nom": "SWISTEK Pierre-Alexandre",
            "email": "pa.swistek@lamouillere.fr",
            "telephone": "06 27 07 69 87"
          },
          {
            "nom": "RENARD Claire",
            "email": "c.renard@lamouillere.fr",
            "telephone": "06 03 69 27 33"
          },
          {
            "nom": "CABUY Aurélie",
            "email": "a.cabuy@lamouillere.fr",
            "telephone": " "
          },
          {
            "nom": "FOULON Cindy",
            "email": "c.foulon@lamouillere.fr",
            "telephone": "02 38 22 60 81"
          }
        ]
      },
      {
        "id": "2",
        "nom": "Service Support",
        "mail":" ",
        "telephone":" ",
        "personnes": [
          {
            "nom": "BOURHIS Clara",
            "email": "c.bourhis@lamouillere.fr",
            "telephone": "06 09 71 02 66"
          },
          {
            "nom": "BERGERARD Melinda",
            "email": "m.bergerard@lamouillere.fr",
            "telephone": " "
          },
          {
            "nom": "REYNAUD Romaric",
            "email": "r.reynaud@lamouillere.fr",
            "telephone": " "
          }
        ]
      },
      {
        "id": "3",
        "nom": "Service Développement et Communication",
        "mail":"developpement@lamouillere.fr",
        "telephone":"02 38 22 60 86",
        "personnes": [
          {
            "nom": "GIL Lauriane",
            "email": "l.gil@lamouillere.fr",
            "telephone": "06 43 85 93 73"
          },
          {
            "nom": "CHAUFOUR Anne-Emmanuelle",
            "email": "a.chaufour@lamouillere.fr",
            "telephone": "06 03 69 27 99"
          },
          {
            "nom": "MASURE Mélissa",
            "email": "m.masure@lamouillere.fr",
            "telephone": " "
          }
        ]
      },
      {
        "id": "4",
        "nom": "Pôle Pedagogique",
        "mail":" ",
        "telephone":" ",
        "personnes": [
          {
            "nom": "CAVALHEIRO Mélanie",
            "email": "m.cavalheiro@lamouillere.fr",
            "telephone": " "
          },
          {
            "nom": "HUMBERT Laura",
            "email": "l.humbert@lamouillere.fr",
            "telephone": "06 09 71 01 44"
          },
          {
            "nom": "MOINGEON Anne",
            "email": "a.moingeon@lamouillere.fr",
            "telephone": "06 09 71 02 39"
          }
        ]
      },
      {
        "id": "5",
        "nom": "Service Coordination",
        "mail":" ",
        "telephone":" ",
        "personnes": [
          {
            "nom": "CBENASSI Stéphane",
            "email": "s.benassi@lamouillere.fr",
            "telephone": "07 86 97 52 40"
          },
          {
            "nom": "BIETRIX Alain",
            "email": "a.bietrix@lamouillere.fr",
            "telephone": "06 43 82 00 68"
          },
          {
            "nom": "VION Sabrine",
            "email": "v.sabrine@lamouillere.fr",
            "telephone": "07 88 32 42 03"
          },
          {
            "nom": "GUIATIN Placidee",
            "email": "p.guiatin@lamouillere.fr",
            "telephone": "06 72 87 34 21"
          },
          {
            "nom": "FEUILLET Fabienne",
            "email": "f.feuillet@lamouillere.fr",
            "telephone": "07 86 97 10 13"
          },
          {
            "nom": "TORRENT Michelle",
            "email": "m.torrent@lamouillere.fr",
            "telephone": "06 09 71 01 06"
          },
          {
            "nom": "MAYSONNAVE Léa",
            "email": "l.maysonnave@lamouillere.fr",
            "telephone": "07 50 14 22 70"
          },
          {
            "nom": "JOSSE Cyrille",
            "email": "c.josse@lamouillere.fr",
            "telephone": "06 43 85 98 70"
          },
          {
            "nom": "THURARD Jean-Luc",
            "email": "j.thurar@lamouillere.fr",
            "telephone": "07 84 22 28 84"
          }
        ]
      },
      {
        "id": "6",
        "nom": "Service Pôle Educatif",
        "mail":"poleeducatif@lamouillere.fr",
        "telephone":"06 07 27 71 02",
        "personnes": [
          {
            "nom": "MUNIER Elisabeth",
            "email": "e.munier@lamouillere.fr",
            "telephone": " "
          },
          {
            "nom": "PELLIER Maxime",
            "email": "e.munier@lamouillere.fr",
            "telephone": " "
          },
          {
            "nom": "MONAR Alexandre",
            "email": "a.monar@lamouillere.fr",
            "telephone": " "
          }
        ]
      },
      {
        "id": "7",
        "nom": "Maintenance SI",
        "mail":"maintenance-si@lamouillere.fr ",
        "telephone":" ",
        "personnes": [
          {
            "nom": "MOINGEON Anne",
            "email": "a.moingeon@lamouillere.fr",
            "telephone": "06 09 71 02 39"
          },
          {
            "nom": "MACHADO Mickael",
            "email": "m.machado@lamouillere.fr",
            "telephone": " "
          },
          {
            "nom": "DARTE Nathan",
            "email": "n.darte@lamouillere.fr",
            "telephone": " "
          }
        ]
      },
      {
        "id": "8",
        "nom":"Service CDR",
        "mail":"cdr@lamouillere.fr",
        "telephone":" ",
        "personnes": [
          {
            "nom": "RIDOUX Nathalie",
            "email": "n.ridoux@lamouillere.fr",
            "telephone": "06 09 71 02 39"
          }
        ]
      },
      {
        "id": "9",
        "nom": "Service Technique",
        "mail":" ",
        "telephone":" ",
        "personnes": [
          {
            "nom": "LEDDET Christophe",
            "email": "c.leddet@lamouillere.fr",
            "telephone": "06 12 95 07 07"
          },
          {
            "nom": "LAUMONIER Benoit",
            "email": "b.laumonier@lamouillère.fr",
            "telephone": " "
          }
        ]
      },
      {
        "id": "10",
        "nom": "Serre Maraichere",
        "mail":" ",
        "telephone":" ",
        "personnes": [
          {
            "nom": "DAUDIN David",
            "email": "d.daudin@lamouillere.fr",
            "telephone": "06 35 83 21 40"
          },
          {
            "nom": "YOBO Barthélémy",
            "email": "b.yobo@lamouillere.fr",
            "telephone": " "
          }
        ]
      }
    ]
  }